imandrax_api/__init__.py
imandrax_api/api_types_version.py
imandrax_api/setup.py
imandrax_api/bindings/__init__.py
imandrax_api/bindings/api_pb2.py
imandrax_api/bindings/api_pb2.pyi
imandrax_api/bindings/api_twirp.py
imandrax_api/bindings/artmsg_pb2.py
imandrax_api/bindings/artmsg_pb2.pyi
imandrax_api/bindings/artmsg_twirp.py
imandrax_api/bindings/error_pb2.py
imandrax_api/bindings/error_pb2.pyi
imandrax_api/bindings/error_twirp.py
imandrax_api/bindings/locs_pb2.py
imandrax_api/bindings/locs_pb2.pyi
imandrax_api/bindings/locs_twirp.py
imandrax_api/bindings/session_pb2.py
imandrax_api/bindings/session_pb2.pyi
imandrax_api/bindings/session_twirp.py
imandrax_api/bindings/simple_api_pb2.py
imandrax_api/bindings/simple_api_pb2.pyi
imandrax_api/bindings/simple_api_twirp.py
imandrax_api/bindings/system_pb2.py
imandrax_api/bindings/system_pb2.pyi
imandrax_api/bindings/system_twirp.py
imandrax_api/bindings/task_pb2.py
imandrax_api/bindings/task_pb2.pyi
imandrax_api/bindings/task_twirp.py
imandrax_api/bindings/utils_pb2.py
imandrax_api/bindings/utils_pb2.pyi
imandrax_api/bindings/utils_twirp.py
imandrax_api/lib/__init__.py
imandrax_api/lib/test_twine.py
imandrax_api/lib/twine.py
imandrax_api/twirp/__init__.py
imandrax_api/twirp/async_client.py
imandrax_api/twirp/client.py
imandrax_api/twirp/context.py
imandrax_api/twirp/ctxkeys.py
imandrax_api/twirp/errors.py
imandrax_api/twirp/exceptions.py
imandrax_api/twirp/hook.py
imandrax_api/twirp/logging.py
imandrax_api-0.18.0.1.dist-info/METADATA
imandrax_api-0.18.0.1.dist-info/WHEEL
imandrax_api-0.18.0.1.dist-info/top_level.txt
imandrax_api-0.18.0.1.dist-info/RECORD
