Metadata-Version: 2.4
Name: imandrax_api
Version: 0.18.0.1
Summary: Imandrax API client library
Requires-Python: >=3.12
Requires-Dist: protobuf==5.29.5
Requires-Dist: requests
Requires-Dist: structlog
Provides-Extra: async
Requires-Dist: aiohttp; extra == "async"
Dynamic: requires-python
